db_client/__init__.py
db_client/client.py
qwamatata_db_client-0.1.2.dist-info/METADATA
qwamatata_db_client-0.1.2.dist-info/WHEEL
qwamatata_db_client-0.1.2.dist-info/top_level.txt
qwamatata_db_client-0.1.2.dist-info/RECORD
