Metadata-Version: 2.4
Name: qwamatata_db_client
Version: 0.1.2
Summary: Database socket client using IlyasMessageProtocol
Author: Ilyas Malyutin
Project-URL: GitHub, https://github.com/Qwamatata/db_client
Requires-Python: >=3.9
Requires-Dist: IlyasMessageProtocol>=0.1.1
